pytest_docker_haproxy_fixtures/__init__.py
pytest_docker_haproxy_fixtures/docker-compose.yml
pytest_docker_haproxy_fixtures/fixtures.py
pytest_docker_haproxy_fixtures/haproxy.insecure.cfg
pytest_docker_haproxy_fixtures/haproxy.secure.cfg
pytest_docker_haproxy_fixtures/utils.py
tests/__init__.py
tests/conftest.py
tests/test_fixtures.py
tests/test_utils.py
pytest_docker_haproxy_fixtures-1.0.0.dist-info/LICENSE.md
pytest_docker_haproxy_fixtures-1.0.0.dist-info/METADATA
pytest_docker_haproxy_fixtures-1.0.0.dist-info/WHEEL
pytest_docker_haproxy_fixtures-1.0.0.dist-info/entry_points.txt
pytest_docker_haproxy_fixtures-1.0.0.dist-info/top_level.txt
pytest_docker_haproxy_fixtures-1.0.0.dist-info/RECORD
