Metadata-Version: 2.1
Name: pytest-docker-haproxy-fixtures
Version: 1.0.0
Summary: Pytest fixtures for testing with haproxy.
Home-page: https://github.com/crashvb/pytest-docker-haproxy-fixtures
Author: Richard Davis
Author-email: crashvb@gmail.com
License: Apache License 2.0
Project-URL: Bug Reports, https://github.com/crashvb/pytest-docker-haproxy-fixtures/issues
Project-URL: Source, https://github.com/crashvb/pytest-docker-haproxy-fixtures
Keywords: docker fixtures haproxy pytest
Platform: UNKNOWN
Classifier: Development Status :: 4 - Beta
Classifier: Intended Audience :: Developers
Classifier: License :: OSI Approved :: Apache Software License
Classifier: Programming Language :: Python :: 3
Classifier: Programming Language :: Python :: 3.8
Classifier: Programming Language :: Python :: 3.9
Classifier: Programming Language :: Python :: 3.10
Classifier: Operating System :: OS Independent
License-File: LICENSE.md
Requires-Dist: bcrypt
Requires-Dist: certifi
Requires-Dist: docker
Requires-Dist: lovely-pytest-docker
Requires-Dist: pyopenssl
Requires-Dist: pytest
Provides-Extra: dev
Requires-Dist: black; extra == "dev"
Requires-Dist: coveralls; extra == "dev"
Requires-Dist: pylint; extra == "dev"
Requires-Dist: pytest; extra == "dev"
Requires-Dist: pytest-cov; extra == "dev"
Requires-Dist: twine; extra == "dev"
Requires-Dist: wheel; extra == "dev"
